README.md
setup.py
shp_way/__init__.py
shp_way/collision_detection.py
shp_way/path_finder.py
shp_way/read_shp.py
shp_way/shapefile_navigator.py
shp_way/spatial_grid.py
shp_way.egg-info/PKG-INFO
shp_way.egg-info/SOURCES.txt
shp_way.egg-info/dependency_links.txt
shp_way.egg-info/requires.txt
shp_way.egg-info/top_level.txt