Metadata-Version: 1.0
Name: shp-way
Version: 1.0
Summary: UNKNOWN
Home-page: https://github.com/bbrownrichardson/ShpWay
Author: Brianna Brown Richardson
Author-email: bbrownrichardson@gmail.com
License: Apache
Platform: UNKNOWN
